py_llm7_code/__init__.py
py_llm7_code-2025.9.121057.dist-info/licenses/LICENSE
py_llm7_code-2025.9.121057.dist-info/METADATA
py_llm7_code-2025.9.121057.dist-info/WHEEL
py_llm7_code-2025.9.121057.dist-info/top_level.txt
py_llm7_code-2025.9.121057.dist-info/RECORD
