Metadata-Version: 2.4
Name: py_llm7_code
Version: 2025.9.121057
Summary: LLM7-powered generator that creates a minimal single-function Python package and runner from a natural-language spec.
Home-page: https://github.com/chigwell/py_llm7_code
Author: Eugene Evstafev
Author-email: chigwel@gmail.com
License: MIT
Project-URL: Source, https://github.com/chigwell/py_llm7_code
Project-URL: Tracker, https://github.com/chigwell/py_llm7_code/issues
Classifier: License :: OSI Approved :: MIT License
Classifier: Development Status :: 3 - Alpha
Classifier: Intended Audience :: Developers
Classifier: Topic :: Software Development :: Code Generators
Classifier: Programming Language :: Python :: 3
Classifier: Programming Language :: Python :: 3 :: Only
Classifier: Programming Language :: Python :: 3.10
Classifier: Programming Language :: Python :: 3.11
Classifier: Programming Language :: Python :: 3.12
Classifier: Operating System :: OS Independent
Requires-Python: >=3.10
License-File: LICENSE
Requires-Dist: langchain-core
Requires-Dist: langchain-llm7
Requires-Dist: llmatch-messages
Dynamic: author
Dynamic: author-email
Dynamic: classifier
Dynamic: description
Dynamic: description-content-type
Dynamic: home-page
Dynamic: license
Dynamic: license-file
Dynamic: project-url
Dynamic: requires-dist
Dynamic: requires-python
Dynamic: summary
